async_modbus/__init__.py
async_modbus/core.py
async_modbus/umodbus_numpy.py
async_modbus-0.2.3.dist-info/licenses/LICENSE
async_modbus-0.2.3.dist-info/METADATA
async_modbus-0.2.3.dist-info/WHEEL
async_modbus-0.2.3.dist-info/top_level.txt
async_modbus-0.2.3.dist-info/zip-safe
async_modbus-0.2.3.dist-info/RECORD
