Metadata-Version: 2.4
Name: async_modbus
Version: 0.2.3
Summary: Async ModBus python library
Home-page: https://github.com/tiagocoutinho/async_modbus
Author: Tiago Coutinho
Author-email: coutinhotiago@gmail.com
License: GNU General Public License v3
Keywords: modbus,tcp,rtu,async_modbus,asyncio
Classifier: Development Status :: 2 - Pre-Alpha
Classifier: Intended Audience :: Developers
Classifier: Natural Language :: English
Classifier: Programming Language :: Python :: 3
Classifier: Programming Language :: Python :: 3 :: Only
Classifier: Programming Language :: Python :: 3.6
Classifier: Programming Language :: Python :: 3.7
Classifier: Programming Language :: Python :: 3.8
Classifier: Programming Language :: Python :: 3.9
Classifier: Programming Language :: Python :: 3.10
Classifier: Programming Language :: Python :: Implementation :: CPython
Requires-Python: >=3.6
License-File: LICENSE
Requires-Dist: connio>=0.2.0
Requires-Dist: umodbus>=1.0.4
Provides-Extra: numpy
Requires-Dist: numpy>=1.1; extra == "numpy"
Provides-Extra: tests
Requires-Dist: pytest>=6; extra == "tests"
Requires-Dist: pytest-asyncio; extra == "tests"
Requires-Dist: pytest-cov; extra == "tests"
Dynamic: license-file
